decisionlib/__init__.py
decisionlib/decisionlib.py
decisionlib/hook.py
decisionlib/schedule.py
decisionlib/shell.py
decisionlib_mhentges-0.0.68.dist-info/METADATA
decisionlib_mhentges-0.0.68.dist-info/WHEEL
decisionlib_mhentges-0.0.68.dist-info/entry_points.txt
decisionlib_mhentges-0.0.68.dist-info/top_level.txt
decisionlib_mhentges-0.0.68.dist-info/RECORD
