Metadata-Version: 2.1
Name: decisionlib-mhentges
Version: 0.0.68
Summary: Taskcluster task-builder
Home-page: UNKNOWN
Author: Mozilla Release Engineering
Author-email: release+python@mozilla.com
License: UNKNOWN
Platform: UNKNOWN
Requires-Python: >=3.6
Requires-Dist: arrow (==0.13.1)
Requires-Dist: gitpython (==2.1.11)
Requires-Dist: json-e (==3.0.0)
Requires-Dist: pyyaml (==5.1)
Requires-Dist: taskcluster (==7.0.1)
